stdkit_cli/__init__.py
stdkit_cli/__main__.py
stdkit_cli/core.py
stdkit_cli/sample_int.py
stdkit_cli-0.1.1.dev3.dist-info/WHEEL
stdkit_cli-0.1.1.dev3.dist-info/entry_points.txt
stdkit_cli-0.1.1.dev3.dist-info/METADATA
stdkit_cli-0.1.1.dev3.dist-info/RECORD
