Metadata-Version: 2.3
Name: stdkit-cli
Version: 0.1.1.dev3
Summary: Pure-stdlib Python tools for the command line
Author: oyghen
Author-email: oyghen <oyghen@duck.com>
Requires-Dist: stdkit>=0.1.1.dev2
Requires-Dist: typer>=0.20.0
Requires-Python: >=3.11
